README.txt
setup.cfg
setup.py
docs/HISTORY.txt
docs/INSTALL.txt
docs/LICENSE.GPL
docs/LICENSE.txt
redomino/__init__.py
redomino.autodelete.egg-info/PKG-INFO
redomino.autodelete.egg-info/SOURCES.txt
redomino.autodelete.egg-info/dependency_links.txt
redomino.autodelete.egg-info/entry_points.txt
redomino.autodelete.egg-info/namespace_packages.txt
redomino.autodelete.egg-info/not-zip-safe
redomino.autodelete.egg-info/paster_plugins.txt
redomino.autodelete.egg-info/requires.txt
redomino.autodelete.egg-info/top_level.txt
redomino/autodelete/HISTORY.txt
redomino/autodelete/README.txt
redomino/autodelete/TODO.txt
redomino/autodelete/__init__.py
redomino/autodelete/annotations.py
redomino/autodelete/config.py
redomino/autodelete/configure.zcml
redomino/autodelete/interfaces.py
redomino/autodelete/profiles.zcml
redomino/autodelete/setuphandlers.py
redomino/autodelete/tests.py
redomino/autodelete/version.txt
redomino/autodelete/Extensions/Install.py
redomino/autodelete/Extensions/__init__.py
redomino/autodelete/Extensions/maintenance_utils.py
redomino/autodelete/browser/__init__.py
redomino/autodelete/browser/configure.zcml
redomino/autodelete/browser/expires_form.py
redomino/autodelete/browser/launch_autodelete.py
redomino/autodelete/browser/templates/control-panel.pt
redomino/autodelete/browser/templates/fieldset.pt
redomino/autodelete/profiles/default/actions.xml
redomino/autodelete/profiles/default/catalog.xml
redomino/autodelete/profiles/default/componentregistry.xml
redomino/autodelete/profiles/default/controlpanel.xml
redomino/autodelete/profiles/default/import_steps.xml
redomino/autodelete/profiles/default/metadata.xml
redomino/autodelete/profiles/default/redomino.autodelete_various.txt
redomino/autodelete/utils/__init__.py
redomino/autodelete/utils/auto_delete.py
redomino/autodelete/utils/interfaces.py
