Metadata-Version: 1.0
Name: redomino.autodelete
Version: 0.1r5
Summary: Plone autodelete objects expired tool
Home-page: http://www.redomino.com/it/labs/progetti/redomino-autodelete
Author: Davide Moro
Author-email: davide.moro@redomino.com
License: GPL
Keywords: plone zope
Platform: UNKNOWN
Classifier: Framework :: Plone
Classifier: Framework :: Zope2
Classifier: Framework :: Zope3
Classifier: Programming Language :: Python
Classifier: Topic :: Software Development :: Libraries :: Python Modules
